{
"type": "FeatureCollection",
"name": "cltr-id-71-a-row",
"crs": { "type": "name", "properties": { "name": "urn:ogc:def:crs:OGC:1.3:CRS84" } },
"features": [
{ "type": "Feature", "properties": { "id": 1, "cluster_id": "71", "column": null, "row": "A" }, "geometry": { "type": "Point", "coordinates": [ 120.976027159685955, 14.30479007127024 ] } },
{ "type": "Feature", "properties": { "id": 2, "cluster_id": "71", "column": null, "row": "A" }, "geometry": { "type": "Point", "coordinates": [ 120.976031645771386, 14.304790326975505 ] } },
{ "type": "Feature", "properties": { "id": 3, "cluster_id": "71", "column": null, "row": "A" }, "geometry": { "type": "Point", "coordinates": [ 120.976037979068479, 14.304790838386037 ] } },
{ "type": "Feature", "properties": { "id": 4, "cluster_id": "71", "column": null, "row": "A" }, "geometry": { "type": "Point", "coordinates": [ 120.976044048478172, 14.304791349796561 ] } },
{ "type": "Feature", "properties": { "id": 5, "cluster_id": "71", "column": null, "row": "A" }, "geometry": { "type": "Point", "coordinates": [ 120.97605064566261, 14.304791861207086 ] } },
{ "type": "Feature", "properties": { "id": 6, "cluster_id": "71", "column": null, "row": "A" }, "geometry": { "type": "Point", "coordinates": [ 120.976058562283967, 14.304792116912347 ] } },
{ "type": "Feature", "properties": { "id": 7, "cluster_id": "71", "column": null, "row": "A" }, "geometry": { "type": "Point", "coordinates": [ 120.97606542335582, 14.30479237261761 ] } },
{ "type": "Feature", "properties": { "id": 8, "cluster_id": "71", "column": null, "row": "A" }, "geometry": { "type": "Point", "coordinates": [ 120.976072812202418, 14.304792884028133 ] } },
{ "type": "Feature", "properties": { "id": 9, "cluster_id": "71", "column": null, "row": "A" }, "geometry": { "type": "Point", "coordinates": [ 120.976085874627614, 14.304793075807087 ] } },
{ "type": "Feature", "properties": { "id": 10, "cluster_id": "71", "column": null, "row": "A" }, "geometry": { "type": "Point", "coordinates": [ 120.976095704432439, 14.304795121449168 ] } },
{ "type": "Feature", "properties": { "id": 11, "cluster_id": "71", "column": null, "row": "A" }, "geometry": { "type": "Point", "coordinates": [ 120.976108041167407, 14.304795313228109 ] } },
{ "type": "Feature", "properties": { "id": 12, "cluster_id": "71", "column": null, "row": "A" }, "geometry": { "type": "Point", "coordinates": [ 120.976119652212049, 14.30479639997546 ] } },
{ "type": "Feature", "properties": { "id": 13, "cluster_id": "71", "column": null, "row": "A" }, "geometry": { "type": "Point", "coordinates": [ 120.976131791031463, 14.304795760712313 ] } },
{ "type": "Feature", "properties": { "id": 14, "cluster_id": "71", "column": null, "row": "A" }, "geometry": { "type": "Point", "coordinates": [ 120.97614815204895, 14.304797167091223 ] } },
{ "type": "Feature", "properties": { "id": 15, "cluster_id": "71", "column": null, "row": "A" }, "geometry": { "type": "Point", "coordinates": [ 120.976159103375167, 14.304798765249066 ] } },
{ "type": "Feature", "properties": { "id": 16, "cluster_id": "71", "column": null, "row": "A" }, "geometry": { "type": "Point", "coordinates": [ 120.976170450532393, 14.304799276659574 ] } }
]
}
