{
"type": "FeatureCollection",
"name": "cltr-id-144-a-row",
"crs": { "type": "name", "properties": { "name": "urn:ogc:def:crs:OGC:1.3:CRS84" } },
"features": [
{ "type": "Feature", "properties": { "fid": 1, "id": 6, "cluster_id": "144", "column": null, "row": "a" }, "geometry": { "type": "Point", "coordinates": [ 120.977354986399078, 14.304738576965283 ] } },
{ "type": "Feature", "properties": { "fid": 2, "id": 7, "cluster_id": "144", "column": null, "row": "a" }, "geometry": { "type": "Point", "coordinates": [ 120.977364855793169, 14.304739351035407 ] } },
{ "type": "Feature", "properties": { "fid": 3, "id": 8, "cluster_id": "144", "column": null, "row": "a" }, "geometry": { "type": "Point", "coordinates": [ 120.977373564082029, 14.30474012510553 ] } },
{ "type": "Feature", "properties": { "fid": 4, "id": 9, "cluster_id": "144", "column": null, "row": "a" }, "geometry": { "type": "Point", "coordinates": [ 120.977382852923526, 14.304740705658123 ] } },
{ "type": "Feature", "properties": { "fid": 5, "id": 10, "cluster_id": "144", "column": null, "row": "a" }, "geometry": { "type": "Point", "coordinates": [ 120.977392722317589, 14.304741673245777 ] } },
{ "type": "Feature", "properties": { "fid": 6, "id": 11, "cluster_id": "144", "column": null, "row": "a" }, "geometry": { "type": "Point", "coordinates": [ 120.977403559299319, 14.30474264083343 ] } },
{ "type": "Feature", "properties": { "fid": 7, "id": 12, "cluster_id": "144", "column": null, "row": "a" }, "geometry": { "type": "Point", "coordinates": [ 120.977415170351179, 14.304743608421088 ] } },
{ "type": "Feature", "properties": { "fid": 8, "id": 13, "cluster_id": "144", "column": null, "row": "a" }, "geometry": { "type": "Point", "coordinates": [ 120.977425813815358, 14.304744382491211 ] } },
{ "type": "Feature", "properties": { "fid": 9, "id": 14, "cluster_id": "144", "column": null, "row": "a" }, "geometry": { "type": "Point", "coordinates": [ 120.977437037832132, 14.304745350078866 ] } },
{ "type": "Feature", "properties": { "fid": 10, "id": 15, "cluster_id": "144", "column": null, "row": "a" }, "geometry": { "type": "Point", "coordinates": [ 120.977448261848934, 14.304746511184051 ] } },
{ "type": "Feature", "properties": { "fid": 11, "id": 16, "cluster_id": "144", "column": null, "row": "a" }, "geometry": { "type": "Point", "coordinates": [ 120.977458518278056, 14.304747478771704 ] } },
{ "type": "Feature", "properties": { "fid": 12, "id": 17, "cluster_id": "144", "column": null, "row": "a" }, "geometry": { "type": "Point", "coordinates": [ 120.977468194154596, 14.304748446359357 ] } },
{ "type": "Feature", "properties": { "fid": 13, "id": 18, "cluster_id": "144", "column": null, "row": "a" }, "geometry": { "type": "Point", "coordinates": [ 120.977477095961007, 14.304749123670714 ] } },
{ "type": "Feature", "properties": { "fid": 14, "id": 19, "cluster_id": "144", "column": null, "row": "a" }, "geometry": { "type": "Point", "coordinates": [ 120.977485997767431, 14.304749994499604 ] } },
{ "type": "Feature", "properties": { "fid": 15, "id": 20, "cluster_id": "144", "column": null, "row": "a" }, "geometry": { "type": "Point", "coordinates": [ 120.977496157437798, 14.304750865328492 ] } },
{ "type": "Feature", "properties": { "fid": 16, "id": 21, "cluster_id": "144", "column": null, "row": "a" }, "geometry": { "type": "Point", "coordinates": [ 120.977505543038035, 14.304751542639849 ] } },
{ "type": "Feature", "properties": { "fid": 17, "id": 1, "cluster_id": "144", "column": null, "row": "a" }, "geometry": { "type": "Point", "coordinates": [ 120.97729867279763, 14.304733545509484 ] } },
{ "type": "Feature", "properties": { "fid": 18, "id": 2, "cluster_id": "144", "column": null, "row": "a" }, "geometry": { "type": "Point", "coordinates": [ 120.977309896814418, 14.304734706614669 ] } },
{ "type": "Feature", "properties": { "fid": 19, "id": 3, "cluster_id": "144", "column": null, "row": "a" }, "geometry": { "type": "Point", "coordinates": [ 120.977322088418859, 14.304735867719854 ] } },
{ "type": "Feature", "properties": { "fid": 20, "id": 4, "cluster_id": "144", "column": null, "row": "a" }, "geometry": { "type": "Point", "coordinates": [ 120.977332925400574, 14.304736448272445 ] } },
{ "type": "Feature", "properties": { "fid": 21, "id": 5, "cluster_id": "144", "column": null, "row": "a" }, "geometry": { "type": "Point", "coordinates": [ 120.977343762382318, 14.304737609377632 ] } }
]
}
