{
"type": "FeatureCollection",
"name": "cltr-id-44-d-row",
"crs": { "type": "name", "properties": { "name": "urn:ogc:def:crs:OGC:1.3:CRS84" } },
"features": [
{ "type": "Feature", "properties": { "id": 1, "cluster_id": "44", "column": null, "row": "D" }, "geometry": { "type": "Point", "coordinates": [ 120.975836971104101, 14.305633577096026 ] } },
{ "type": "Feature", "properties": { "id": 2, "cluster_id": "44", "column": null, "row": "D" }, "geometry": { "type": "Point", "coordinates": [ 120.975837267977411, 14.305629549748359 ] } },
{ "type": "Feature", "properties": { "id": 3, "cluster_id": "44", "column": null, "row": "D" }, "geometry": { "type": "Point", "coordinates": [ 120.975829914093836, 14.305619717893375 ] } },
{ "type": "Feature", "properties": { "id": 4, "cluster_id": "44", "column": null, "row": "D" }, "geometry": { "type": "Point", "coordinates": [ 120.975836239242653, 14.305620123842738 ] } },
{ "type": "Feature", "properties": { "id": 5, "cluster_id": "44", "column": null, "row": "D" }, "geometry": { "type": "Point", "coordinates": [ 120.975845293878336, 14.305620699178164 ] } },
{ "type": "Feature", "properties": { "id": 6, "cluster_id": "44", "column": null, "row": "D" }, "geometry": { "type": "Point", "coordinates": [ 120.975853606330745, 14.305621418347449 ] } },
{ "type": "Feature", "properties": { "id": 7, "cluster_id": "44", "column": null, "row": "D" }, "geometry": { "type": "Point", "coordinates": [ 120.975863254713033, 14.305621706015163 ] } },
{ "type": "Feature", "properties": { "id": 8, "cluster_id": "44", "column": null, "row": "D" }, "geometry": { "type": "Point", "coordinates": [ 120.975875129645047, 14.305622425184444 ] } },
{ "type": "Feature", "properties": { "id": 9, "cluster_id": "44", "column": null, "row": "D" }, "geometry": { "type": "Point", "coordinates": [ 120.975886707703779, 14.305623719689141 ] } },
{ "type": "Feature", "properties": { "id": 10, "cluster_id": "44", "column": null, "row": "D" }, "geometry": { "type": "Point", "coordinates": [ 120.975895168592842, 14.305623863522994 ] } },
{ "type": "Feature", "properties": { "id": 11, "cluster_id": "44", "column": null, "row": "D" }, "geometry": { "type": "Point", "coordinates": [ 120.975902145115398, 14.305624726526121 ] } },
{ "type": "Feature", "properties": { "id": 12, "cluster_id": "44", "column": null, "row": "D" }, "geometry": { "type": "Point", "coordinates": [ 120.975918621583588, 14.305626021030807 ] } },
{ "type": "Feature", "properties": { "id": 13, "cluster_id": "44", "column": null, "row": "D" }, "geometry": { "type": "Point", "coordinates": [ 120.97593079338894, 14.305626740200067 ] } },
{ "type": "Feature", "properties": { "id": 14, "cluster_id": "44", "column": null, "row": "D" }, "geometry": { "type": "Point", "coordinates": [ 120.975942519884285, 14.305627171701628 ] } },
{ "type": "Feature", "properties": { "id": 15, "cluster_id": "44", "column": null, "row": "D" }, "geometry": { "type": "Point", "coordinates": [ 120.975950980773376, 14.30562774703704 ] } },
{ "type": "Feature", "properties": { "id": 16, "cluster_id": "44", "column": null, "row": "D" }, "geometry": { "type": "Point", "coordinates": [ 120.975960480718982, 14.305628178538596 ] } },
{ "type": "Feature", "properties": { "id": 17, "cluster_id": "44", "column": null, "row": "D" }, "geometry": { "type": "Point", "coordinates": [ 120.975973988454157, 14.30562904154171 ] } },
{ "type": "Feature", "properties": { "id": 18, "cluster_id": "44", "column": null, "row": "D" }, "geometry": { "type": "Point", "coordinates": [ 120.975986308696136, 14.305629904544812 ] } },
{ "type": "Feature", "properties": { "id": 19, "cluster_id": "44", "column": null, "row": "D" }, "geometry": { "type": "Point", "coordinates": [ 120.975999519558002, 14.30563047988022 ] } },
{ "type": "Feature", "properties": { "id": 20, "cluster_id": "44", "column": null, "row": "D" }, "geometry": { "type": "Point", "coordinates": [ 120.976015763049446, 14.30563163533912 ] } }
]
}
