{
"type": "FeatureCollection",
"name": "cltr-id-46-a-row",
"crs": { "type": "name", "properties": { "name": "urn:ogc:def:crs:OGC:1.3:CRS84" } },
"features": [
{ "type": "Feature", "properties": { "fid": 1, "id": 1, "cluster_id": "46", "column": null, "row": "A" }, "geometry": { "type": "Point", "coordinates": [ 120.975839950491618, 14.305498750821638 ] } },
{ "type": "Feature", "properties": { "fid": 2, "id": 2, "cluster_id": "46", "column": null, "row": "A" }, "geometry": { "type": "Point", "coordinates": [ 120.975840395801555, 14.305494867312413 ] } },
{ "type": "Feature", "properties": { "fid": 3, "id": 3, "cluster_id": "46", "column": null, "row": "A" }, "geometry": { "type": "Point", "coordinates": [ 120.975842562626369, 14.305477614810364 ] } },
{ "type": "Feature", "properties": { "fid": 4, "id": 4, "cluster_id": "46", "column": null, "row": "A" }, "geometry": { "type": "Point", "coordinates": [ 120.975849602449387, 14.305478041155313 ] } },
{ "type": "Feature", "properties": { "fid": 5, "id": 5, "cluster_id": "46", "column": null, "row": "A" }, "geometry": { "type": "Point", "coordinates": [ 120.975856055620469, 14.305478467500267 ] } },
{ "type": "Feature", "properties": { "fid": 6, "id": 6, "cluster_id": "46", "column": null, "row": "A" }, "geometry": { "type": "Point", "coordinates": [ 120.975862362128581, 14.305478893845208 ] } },
{ "type": "Feature", "properties": { "fid": 7, "id": 7, "cluster_id": "46", "column": null, "row": "A" }, "geometry": { "type": "Point", "coordinates": [ 120.975869255288615, 14.305479320190162 ] } },
{ "type": "Feature", "properties": { "fid": 8, "id": 8, "cluster_id": "46", "column": null, "row": "A" }, "geometry": { "type": "Point", "coordinates": [ 120.975876588437572, 14.305480030765073 ] } },
{ "type": "Feature", "properties": { "fid": 9, "id": 9, "cluster_id": "46", "column": null, "row": "A" }, "geometry": { "type": "Point", "coordinates": [ 120.975887294835061, 14.305480599225001 ] } },
{ "type": "Feature", "properties": { "fid": 10, "id": 10, "cluster_id": "46", "column": null, "row": "A" }, "geometry": { "type": "Point", "coordinates": [ 120.975895654624892, 14.305481025569945 ] } },
{ "type": "Feature", "properties": { "fid": 11, "id": 11, "cluster_id": "46", "column": null, "row": "A" }, "geometry": { "type": "Point", "coordinates": [ 120.975903281099818, 14.305481594029873 ] } },
{ "type": "Feature", "properties": { "fid": 12, "id": 12, "cluster_id": "46", "column": null, "row": "A" }, "geometry": { "type": "Point", "coordinates": [ 120.975909734270914, 14.305482162489799 ] } },
{ "type": "Feature", "properties": { "fid": 13, "id": 13, "cluster_id": "46", "column": null, "row": "A" }, "geometry": { "type": "Point", "coordinates": [ 120.975917800734777, 14.305482730949722 ] } },
{ "type": "Feature", "properties": { "fid": 14, "id": 14, "cluster_id": "46", "column": null, "row": "A" }, "geometry": { "type": "Point", "coordinates": [ 120.975926600513517, 14.30548315729466 ] } },
{ "type": "Feature", "properties": { "fid": 15, "id": 15, "cluster_id": "46", "column": null, "row": "A" }, "geometry": { "type": "Point", "coordinates": [ 120.975934373651455, 14.305483441524627 ] } },
{ "type": "Feature", "properties": { "fid": 16, "id": 16, "cluster_id": "46", "column": null, "row": "A" }, "geometry": { "type": "Point", "coordinates": [ 120.975941780131905, 14.305484009984545 ] } },
{ "type": "Feature", "properties": { "fid": 17, "id": 17, "cluster_id": "46", "column": null, "row": "A" }, "geometry": { "type": "Point", "coordinates": [ 120.975954319816623, 14.305484862674422 ] } },
{ "type": "Feature", "properties": { "fid": 18, "id": 18, "cluster_id": "46", "column": null, "row": "A" }, "geometry": { "type": "Point", "coordinates": [ 120.975966932832847, 14.305485715364297 ] } },
{ "type": "Feature", "properties": { "fid": 19, "id": 19, "cluster_id": "46", "column": null, "row": "A" }, "geometry": { "type": "Point", "coordinates": [ 120.975984385727401, 14.305486710169141 ] } },
{ "type": "Feature", "properties": { "fid": 20, "id": 20, "cluster_id": "46", "column": null, "row": "A" }, "geometry": { "type": "Point", "coordinates": [ 120.976002718599801, 14.305487989203939 ] } },
{ "type": "Feature", "properties": { "fid": 21, "id": 21, "cluster_id": "46", "column": null, "row": "A" }, "geometry": { "type": "Point", "coordinates": [ 120.976014230369415, 14.305488811330612 ] } },
{ "type": "Feature", "properties": { "fid": 22, "id": 22, "cluster_id": "46", "column": null, "row": "A" }, "geometry": { "type": "Point", "coordinates": [ 120.976019722525464, 14.305489530498969 ] } },
{ "type": "Feature", "properties": { "fid": 23, "id": 23, "cluster_id": "46", "column": null, "row": "A" }, "geometry": { "type": "Point", "coordinates": [ 120.976027195905999, 14.305489420020422 ] } }
]
}
