{
"type": "FeatureCollection",
"name": "cltr-id-66-d-row",
"crs": { "type": "name", "properties": { "name": "urn:ogc:def:crs:OGC:1.3:CRS84" } },
"features": [
{ "type": "Feature", "properties": { "id": 1, "cluster_id": "66", "column": null, "row": "D" }, "geometry": { "type": "Point", "coordinates": [ 120.9760319508908, 14.304699391644075 ] } },
{ "type": "Feature", "properties": { "id": 2, "cluster_id": "66", "column": null, "row": "D" }, "geometry": { "type": "Point", "coordinates": [ 120.976032371461315, 14.30469450128175 ] } },
{ "type": "Feature", "properties": { "id": 3, "cluster_id": "66", "column": null, "row": "D" }, "geometry": { "type": "Point", "coordinates": [ 120.976023328729298, 14.304681643350794 ] } },
{ "type": "Feature", "properties": { "id": 4, "cluster_id": "66", "column": null, "row": "D" }, "geometry": { "type": "Point", "coordinates": [ 120.976027084728145, 14.304682003928818 ] } },
{ "type": "Feature", "properties": { "id": 5, "cluster_id": "66", "column": null, "row": "D" }, "geometry": { "type": "Point", "coordinates": [ 120.976031983137602, 14.30468233954195 ] } },
{ "type": "Feature", "properties": { "id": 6, "cluster_id": "66", "column": null, "row": "D" }, "geometry": { "type": "Point", "coordinates": [ 120.976036337279368, 14.304682723099818 ] } },
{ "type": "Feature", "properties": { "id": 7, "cluster_id": "66", "column": null, "row": "D" }, "geometry": { "type": "Point", "coordinates": [ 120.97604079037886, 14.304682962823479 ] } },
{ "type": "Feature", "properties": { "id": 8, "cluster_id": "66", "column": null, "row": "D" }, "geometry": { "type": "Point", "coordinates": [ 120.976045391915036, 14.304683298436615 ] } },
{ "type": "Feature", "properties": { "id": 9, "cluster_id": "66", "column": null, "row": "D" }, "geometry": { "type": "Point", "coordinates": [ 120.976049943972299, 14.304683825828677 ] } },
{ "type": "Feature", "properties": { "id": 10, "cluster_id": "66", "column": null, "row": "D" }, "geometry": { "type": "Point", "coordinates": [ 120.97605449602959, 14.304684065552346 ] } },
{ "type": "Feature", "properties": { "id": 11, "cluster_id": "66", "column": null, "row": "D" }, "geometry": { "type": "Point", "coordinates": [ 120.976064045454066, 14.304684784723339 ] } },
{ "type": "Feature", "properties": { "id": 12, "cluster_id": "66", "column": null, "row": "D" }, "geometry": { "type": "Point", "coordinates": [ 120.976073743315226, 14.304685743617997 ] } },
{ "type": "Feature", "properties": { "id": 13, "cluster_id": "66", "column": null, "row": "D" }, "geometry": { "type": "Point", "coordinates": [ 120.976084232838502, 14.304686894291578 ] } },
{ "type": "Feature", "properties": { "id": 14, "cluster_id": "66", "column": null, "row": "D" }, "geometry": { "type": "Point", "coordinates": [ 120.976095118192859, 14.304687469628366 ] } },
{ "type": "Feature", "properties": { "id": 15, "cluster_id": "66", "column": null, "row": "D" }, "geometry": { "type": "Point", "coordinates": [ 120.976107487913765, 14.304688068937516 ] } },
{ "type": "Feature", "properties": { "id": 16, "cluster_id": "66", "column": null, "row": "D" }, "geometry": { "type": "Point", "coordinates": [ 120.976119560761319, 14.304689027832158 ] } },
{ "type": "Feature", "properties": { "id": 17, "cluster_id": "66", "column": null, "row": "D" }, "geometry": { "type": "Point", "coordinates": [ 120.976132920059854, 14.304689890837331 ] } },
{ "type": "Feature", "properties": { "id": 18, "cluster_id": "66", "column": null, "row": "D" }, "geometry": { "type": "Point", "coordinates": [ 120.97615023766906, 14.30469113740036 ] } },
{ "type": "Feature", "properties": { "id": 19, "cluster_id": "66", "column": null, "row": "D" }, "geometry": { "type": "Point", "coordinates": [ 120.976164487587482, 14.304692288073914 ] } },
{ "type": "Feature", "properties": { "id": 20, "cluster_id": "66", "column": null, "row": "D" }, "geometry": { "type": "Point", "coordinates": [ 120.97618739631055, 14.304694014084232 ] } },
{ "type": "Feature", "properties": { "id": 21, "cluster_id": "66", "column": null, "row": "D" }, "geometry": { "type": "Point", "coordinates": [ 120.976199939946625, 14.304694948766684 ] } }
]
}
