{
"type": "FeatureCollection",
"name": "cltr-id-45-c-row",
"crs": { "type": "name", "properties": { "name": "urn:ogc:def:crs:OGC:1.3:CRS84" } },
"features": [
{ "type": "Feature", "properties": { "fid": 1, "id": 1, "cluster_id": "45", "column": null, "row": "C" }, "geometry": { "type": "Point", "coordinates": [ 120.975838444562569, 14.305521019992575 ] } },
{ "type": "Feature", "properties": { "fid": 2, "id": 2, "cluster_id": "45", "column": null, "row": "C" }, "geometry": { "type": "Point", "coordinates": [ 120.975846319267035, 14.305521613842158 ] } },
{ "type": "Feature", "properties": { "fid": 3, "id": 3, "cluster_id": "45", "column": null, "row": "C" }, "geometry": { "type": "Point", "coordinates": [ 120.975852625775133, 14.305522182302095 ] } },
{ "type": "Feature", "properties": { "fid": 4, "id": 4, "cluster_id": "45", "column": null, "row": "C" }, "geometry": { "type": "Point", "coordinates": [ 120.975859665598151, 14.305522608647044 ] } },
{ "type": "Feature", "properties": { "fid": 5, "id": 5, "cluster_id": "45", "column": null, "row": "C" }, "geometry": { "type": "Point", "coordinates": [ 120.975866118769233, 14.305523034991998 ] } },
{ "type": "Feature", "properties": { "fid": 6, "id": 6, "cluster_id": "45", "column": null, "row": "C" }, "geometry": { "type": "Point", "coordinates": [ 120.975872425277345, 14.305523461336939 ] } },
{ "type": "Feature", "properties": { "fid": 7, "id": 7, "cluster_id": "45", "column": null, "row": "C" }, "geometry": { "type": "Point", "coordinates": [ 120.975879318437379, 14.305523887681893 ] } },
{ "type": "Feature", "properties": { "fid": 8, "id": 8, "cluster_id": "45", "column": null, "row": "C" }, "geometry": { "type": "Point", "coordinates": [ 120.975886651586336, 14.305524598256804 ] } },
{ "type": "Feature", "properties": { "fid": 9, "id": 9, "cluster_id": "45", "column": null, "row": "C" }, "geometry": { "type": "Point", "coordinates": [ 120.975897357983825, 14.305525166716732 ] } },
{ "type": "Feature", "properties": { "fid": 10, "id": 10, "cluster_id": "45", "column": null, "row": "C" }, "geometry": { "type": "Point", "coordinates": [ 120.975905717773657, 14.305525593061676 ] } },
{ "type": "Feature", "properties": { "fid": 11, "id": 11, "cluster_id": "45", "column": null, "row": "C" }, "geometry": { "type": "Point", "coordinates": [ 120.975913344248582, 14.305526161521604 ] } },
{ "type": "Feature", "properties": { "fid": 12, "id": 12, "cluster_id": "45", "column": null, "row": "C" }, "geometry": { "type": "Point", "coordinates": [ 120.975919797419678, 14.30552672998153 ] } },
{ "type": "Feature", "properties": { "fid": 13, "id": 13, "cluster_id": "45", "column": null, "row": "C" }, "geometry": { "type": "Point", "coordinates": [ 120.975927863883541, 14.305527298441453 ] } },
{ "type": "Feature", "properties": { "fid": 14, "id": 14, "cluster_id": "45", "column": null, "row": "C" }, "geometry": { "type": "Point", "coordinates": [ 120.975936663662281, 14.305527724786391 ] } },
{ "type": "Feature", "properties": { "fid": 15, "id": 15, "cluster_id": "45", "column": null, "row": "C" }, "geometry": { "type": "Point", "coordinates": [ 120.975944436800219, 14.305528009016358 ] } },
{ "type": "Feature", "properties": { "fid": 16, "id": 16, "cluster_id": "45", "column": null, "row": "C" }, "geometry": { "type": "Point", "coordinates": [ 120.975951843280669, 14.305528577476275 ] } },
{ "type": "Feature", "properties": { "fid": 17, "id": 17, "cluster_id": "45", "column": null, "row": "C" }, "geometry": { "type": "Point", "coordinates": [ 120.975964382965387, 14.305529430166153 ] } },
{ "type": "Feature", "properties": { "fid": 18, "id": 18, "cluster_id": "45", "column": null, "row": "C" }, "geometry": { "type": "Point", "coordinates": [ 120.975976995981611, 14.305530282856028 ] } },
{ "type": "Feature", "properties": { "fid": 19, "id": 19, "cluster_id": "45", "column": null, "row": "C" }, "geometry": { "type": "Point", "coordinates": [ 120.975994448876165, 14.305531277660872 ] } },
{ "type": "Feature", "properties": { "fid": 20, "id": 20, "cluster_id": "45", "column": null, "row": "C" }, "geometry": { "type": "Point", "coordinates": [ 120.976012781748565, 14.30553255669567 ] } },
{ "type": "Feature", "properties": { "fid": 21, "id": 21, "cluster_id": "45", "column": null, "row": "C" }, "geometry": { "type": "Point", "coordinates": [ 120.976024293518179, 14.305533378822343 ] } },
{ "type": "Feature", "properties": { "fid": 22, "id": 22, "cluster_id": "45", "column": null, "row": "C" }, "geometry": { "type": "Point", "coordinates": [ 120.976018366694205, 14.305523661180407 ] } },
{ "type": "Feature", "properties": { "fid": 23, "id": 23, "cluster_id": "45", "column": null, "row": "C" }, "geometry": { "type": "Point", "coordinates": [ 120.976019246672053, 14.30551698177589 ] } }
]
}
