{
"type": "FeatureCollection",
"name": "cltr-id-52-a-row",
"crs": { "type": "name", "properties": { "name": "urn:ogc:def:crs:OGC:1.3:CRS84" } },
"features": [
{ "type": "Feature", "properties": { "id": 1, "cluster_id": "52", "column": null, "row": "A" }, "geometry": { "type": "Point", "coordinates": [ 120.97582813285392, 14.305680765469168 ] } },
{ "type": "Feature", "properties": { "id": 2, "cluster_id": "52", "column": null, "row": "A" }, "geometry": { "type": "Point", "coordinates": [ 120.975836172423485, 14.305681597008483 ] } },
{ "type": "Feature", "properties": { "id": 3, "cluster_id": "52", "column": null, "row": "A" }, "geometry": { "type": "Point", "coordinates": [ 120.975845375495808, 14.305682747679068 ] } },
{ "type": "Feature", "properties": { "id": 4, "cluster_id": "52", "column": null, "row": "A" }, "geometry": { "type": "Point", "coordinates": [ 120.975854578568132, 14.305682747679068 ] } },
{ "type": "Feature", "properties": { "id": 5, "cluster_id": "52", "column": null, "row": "A" }, "geometry": { "type": "Point", "coordinates": [ 120.97586289102054, 14.305682747679068 ] } },
{ "type": "Feature", "properties": { "id": 6, "cluster_id": "52", "column": null, "row": "A" }, "geometry": { "type": "Point", "coordinates": [ 120.975871500346244, 14.305683898349651 ] } },
{ "type": "Feature", "properties": { "id": 7, "cluster_id": "52", "column": null, "row": "A" }, "geometry": { "type": "Point", "coordinates": [ 120.975881297165174, 14.305684761352582 ] } },
{ "type": "Feature", "properties": { "id": 8, "cluster_id": "52", "column": null, "row": "A" }, "geometry": { "type": "Point", "coordinates": [ 120.975891093984103, 14.305685049020228 ] } },
{ "type": "Feature", "properties": { "id": 9, "cluster_id": "52", "column": null, "row": "A" }, "geometry": { "type": "Point", "coordinates": [ 120.975901187676314, 14.305685912023153 ] } },
{ "type": "Feature", "properties": { "id": 10, "cluster_id": "52", "column": null, "row": "A" }, "geometry": { "type": "Point", "coordinates": [ 120.975910390748638, 14.305686487358436 ] } },
{ "type": "Feature", "properties": { "id": 11, "cluster_id": "52", "column": null, "row": "A" }, "geometry": { "type": "Point", "coordinates": [ 120.975920187567567, 14.305687062693723 ] } },
{ "type": "Feature", "properties": { "id": 12, "cluster_id": "52", "column": null, "row": "A" }, "geometry": { "type": "Point", "coordinates": [ 120.97592850001999, 14.305687350361362 ] } },
{ "type": "Feature", "properties": { "id": 13, "cluster_id": "52", "column": null, "row": "A" }, "geometry": { "type": "Point", "coordinates": [ 120.975937999965595, 14.305688213364281 ] } },
{ "type": "Feature", "properties": { "id": 14, "cluster_id": "52", "column": null, "row": "A" }, "geometry": { "type": "Point", "coordinates": [ 120.97595135926413, 14.305688644865741 ] } },
{ "type": "Feature", "properties": { "id": 15, "cluster_id": "52", "column": null, "row": "A" }, "geometry": { "type": "Point", "coordinates": [ 120.975964124816073, 14.305690227037745 ] } },
{ "type": "Feature", "properties": { "id": 16, "cluster_id": "52", "column": null, "row": "A" }, "geometry": { "type": "Point", "coordinates": [ 120.975977466393502, 14.305690822959813 ] } },
{ "type": "Feature", "properties": { "id": 17, "cluster_id": "52", "column": null, "row": "A" }, "geometry": { "type": "Point", "coordinates": [ 120.975988846536708, 14.305691590072863 ] } },
{ "type": "Feature", "properties": { "id": 18, "cluster_id": "52", "column": null, "row": "A" }, "geometry": { "type": "Point", "coordinates": [ 120.976003492286225, 14.305692548964155 ] } }
]
}
