{
"type": "FeatureCollection",
"name": "cltr-id-42-d-row",
"crs": { "type": "name", "properties": { "name": "urn:ogc:def:crs:OGC:1.3:CRS84" } },
"features": [
{ "type": "Feature", "properties": { "fid": 1, "id": 1, "cluster_id": "42", "column": null, "row": "D" }, "geometry": { "type": "Point", "coordinates": [ 120.97583348052342, 14.305768403302816 ] } },
{ "type": "Feature", "properties": { "fid": 2, "id": 2, "cluster_id": "42", "column": null, "row": "D" }, "geometry": { "type": "Point", "coordinates": [ 120.975833925833356, 14.305764519793591 ] } },
{ "type": "Feature", "properties": { "fid": 3, "id": 3, "cluster_id": "42", "column": null, "row": "D" }, "geometry": { "type": "Point", "coordinates": [ 120.975823854054582, 14.305755375506518 ] } },
{ "type": "Feature", "properties": { "fid": 4, "id": 4, "cluster_id": "42", "column": null, "row": "D" }, "geometry": { "type": "Point", "coordinates": [ 120.9758308938776, 14.305755801851467 ] } },
{ "type": "Feature", "properties": { "fid": 5, "id": 5, "cluster_id": "42", "column": null, "row": "D" }, "geometry": { "type": "Point", "coordinates": [ 120.975837347048682, 14.305756228196421 ] } },
{ "type": "Feature", "properties": { "fid": 6, "id": 6, "cluster_id": "42", "column": null, "row": "D" }, "geometry": { "type": "Point", "coordinates": [ 120.975843653556794, 14.305756654541362 ] } },
{ "type": "Feature", "properties": { "fid": 7, "id": 7, "cluster_id": "42", "column": null, "row": "D" }, "geometry": { "type": "Point", "coordinates": [ 120.975850546716828, 14.305757080886316 ] } },
{ "type": "Feature", "properties": { "fid": 8, "id": 8, "cluster_id": "42", "column": null, "row": "D" }, "geometry": { "type": "Point", "coordinates": [ 120.975857879865785, 14.305757791461227 ] } },
{ "type": "Feature", "properties": { "fid": 9, "id": 9, "cluster_id": "42", "column": null, "row": "D" }, "geometry": { "type": "Point", "coordinates": [ 120.975868586263275, 14.305758359921155 ] } },
{ "type": "Feature", "properties": { "fid": 10, "id": 10, "cluster_id": "42", "column": null, "row": "D" }, "geometry": { "type": "Point", "coordinates": [ 120.975876946053106, 14.305758786266098 ] } },
{ "type": "Feature", "properties": { "fid": 11, "id": 11, "cluster_id": "42", "column": null, "row": "D" }, "geometry": { "type": "Point", "coordinates": [ 120.975884572528031, 14.305759354726026 ] } },
{ "type": "Feature", "properties": { "fid": 12, "id": 12, "cluster_id": "42", "column": null, "row": "D" }, "geometry": { "type": "Point", "coordinates": [ 120.975891025699127, 14.305759923185953 ] } },
{ "type": "Feature", "properties": { "fid": 13, "id": 13, "cluster_id": "42", "column": null, "row": "D" }, "geometry": { "type": "Point", "coordinates": [ 120.97589909216299, 14.305760491645875 ] } },
{ "type": "Feature", "properties": { "fid": 14, "id": 14, "cluster_id": "42", "column": null, "row": "D" }, "geometry": { "type": "Point", "coordinates": [ 120.975907891941731, 14.305760917990813 ] } },
{ "type": "Feature", "properties": { "fid": 15, "id": 15, "cluster_id": "42", "column": null, "row": "D" }, "geometry": { "type": "Point", "coordinates": [ 120.975915665079668, 14.305761202220781 ] } },
{ "type": "Feature", "properties": { "fid": 16, "id": 16, "cluster_id": "42", "column": null, "row": "D" }, "geometry": { "type": "Point", "coordinates": [ 120.975923071560118, 14.305761770680698 ] } },
{ "type": "Feature", "properties": { "fid": 17, "id": 17, "cluster_id": "42", "column": null, "row": "D" }, "geometry": { "type": "Point", "coordinates": [ 120.975935611244836, 14.305762623370576 ] } },
{ "type": "Feature", "properties": { "fid": 18, "id": 18, "cluster_id": "42", "column": null, "row": "D" }, "geometry": { "type": "Point", "coordinates": [ 120.97594822426106, 14.30576347606045 ] } },
{ "type": "Feature", "properties": { "fid": 19, "id": 19, "cluster_id": "42", "column": null, "row": "D" }, "geometry": { "type": "Point", "coordinates": [ 120.975965677155614, 14.305764470865295 ] } },
{ "type": "Feature", "properties": { "fid": 20, "id": 20, "cluster_id": "42", "column": null, "row": "D" }, "geometry": { "type": "Point", "coordinates": [ 120.975984010028014, 14.305765749900093 ] } },
{ "type": "Feature", "properties": { "fid": 21, "id": 21, "cluster_id": "42", "column": null, "row": "D" }, "geometry": { "type": "Point", "coordinates": [ 120.975995521797628, 14.305766572026766 ] } },
{ "type": "Feature", "properties": { "fid": 22, "id": 22, "cluster_id": "42", "column": null, "row": "D" }, "geometry": { "type": "Point", "coordinates": [ 120.976001013953677, 14.305767291195123 ] } },
{ "type": "Feature", "properties": { "fid": 23, "id": 23, "cluster_id": "42", "column": null, "row": "D" }, "geometry": { "type": "Point", "coordinates": [ 120.976008487334212, 14.305767180716575 ] } }
]
}
