{
"type": "FeatureCollection",
"name": "cltr-id-143-a-row",
"crs": { "type": "name", "properties": { "name": "urn:ogc:def:crs:OGC:1.3:CRS84" } },
"features": [
{ "type": "Feature", "properties": { "fid": 1, "id": 1, "cluster_id": "143", "column": null, "row": "a" }, "geometry": { "type": "Point", "coordinates": [ 120.977281166959784, 14.304836581983587 ] } },
{ "type": "Feature", "properties": { "fid": 2, "id": 2, "cluster_id": "143", "column": null, "row": "a" }, "geometry": { "type": "Point", "coordinates": [ 120.977294679321361, 14.304838004337437 ] } },
{ "type": "Feature", "properties": { "fid": 3, "id": 3, "cluster_id": "143", "column": null, "row": "a" }, "geometry": { "type": "Point", "coordinates": [ 120.97730890285986, 14.304839071102826 ] } },
{ "type": "Feature", "properties": { "fid": 4, "id": 4, "cluster_id": "143", "column": null, "row": "a" }, "geometry": { "type": "Point", "coordinates": [ 120.977325259929174, 14.304840493456677 ] } },
{ "type": "Feature", "properties": { "fid": 5, "id": 5, "cluster_id": "143", "column": null, "row": "a" }, "geometry": { "type": "Point", "coordinates": [ 120.977339483467674, 14.304841915810528 ] } },
{ "type": "Feature", "properties": { "fid": 6, "id": 6, "cluster_id": "143", "column": null, "row": "a" }, "geometry": { "type": "Point", "coordinates": [ 120.977352995829264, 14.304842982575916 ] } },
{ "type": "Feature", "properties": { "fid": 7, "id": 7, "cluster_id": "143", "column": null, "row": "a" }, "geometry": { "type": "Point", "coordinates": [ 120.977365797013917, 14.304844049341304 ] } },
{ "type": "Feature", "properties": { "fid": 8, "id": 8, "cluster_id": "143", "column": null, "row": "a" }, "geometry": { "type": "Point", "coordinates": [ 120.977378953787053, 14.304844760518231 ] } },
{ "type": "Feature", "properties": { "fid": 9, "id": 9, "cluster_id": "143", "column": null, "row": "a" }, "geometry": { "type": "Point", "coordinates": [ 120.977392110560203, 14.304846538460547 ] } },
{ "type": "Feature", "properties": { "fid": 10, "id": 10, "cluster_id": "143", "column": null, "row": "a" }, "geometry": { "type": "Point", "coordinates": [ 120.977403844979463, 14.304847249637472 ] } },
{ "type": "Feature", "properties": { "fid": 11, "id": 11, "cluster_id": "143", "column": null, "row": "a" }, "geometry": { "type": "Point", "coordinates": [ 120.977416646164116, 14.304849027579785 ] } },
{ "type": "Feature", "properties": { "fid": 12, "id": 12, "cluster_id": "143", "column": null, "row": "a" }, "geometry": { "type": "Point", "coordinates": [ 120.977429802937252, 14.304849738756712 ] } },
{ "type": "Feature", "properties": { "fid": 13, "id": 13, "cluster_id": "143", "column": null, "row": "a" }, "geometry": { "type": "Point", "coordinates": [ 120.977442604121919, 14.304851161110564 ] } },
{ "type": "Feature", "properties": { "fid": 14, "id": 14, "cluster_id": "143", "column": null, "row": "a" }, "geometry": { "type": "Point", "coordinates": [ 120.977457183248887, 14.304851872287488 ] } },
{ "type": "Feature", "properties": { "fid": 15, "id": 15, "cluster_id": "143", "column": null, "row": "a" }, "geometry": { "type": "Point", "coordinates": [ 120.977472117964325, 14.304853294641338 ] } },
{ "type": "Feature", "properties": { "fid": 16, "id": 16, "cluster_id": "143", "column": null, "row": "a" }, "geometry": { "type": "Point", "coordinates": [ 120.97748847503361, 14.304854361406727 ] } }
]
}
