{
"type": "FeatureCollection",
"name": "cltr-id-39-a-row",
"crs": { "type": "name", "properties": { "name": "urn:ogc:def:crs:OGC:1.3:CRS84" } },
"features": [
{ "type": "Feature", "properties": { "id": 1, "cluster_id": "39", "column": null, "row": "A" }, "geometry": { "type": "Point", "coordinates": [ 120.975808018784605, 14.305929384847413 ] } },
{ "type": "Feature", "properties": { "id": 2, "cluster_id": "39", "column": null, "row": "A" }, "geometry": { "type": "Point", "coordinates": [ 120.97581589348907, 14.305929978696996 ] } },
{ "type": "Feature", "properties": { "id": 3, "cluster_id": "39", "column": null, "row": "A" }, "geometry": { "type": "Point", "coordinates": [ 120.975822199997168, 14.305930547156933 ] } },
{ "type": "Feature", "properties": { "id": 4, "cluster_id": "39", "column": null, "row": "A" }, "geometry": { "type": "Point", "coordinates": [ 120.975829239820186, 14.305930973501882 ] } },
{ "type": "Feature", "properties": { "id": 5, "cluster_id": "39", "column": null, "row": "A" }, "geometry": { "type": "Point", "coordinates": [ 120.975835692991268, 14.305931399846836 ] } },
{ "type": "Feature", "properties": { "id": 6, "cluster_id": "39", "column": null, "row": "A" }, "geometry": { "type": "Point", "coordinates": [ 120.97584199949938, 14.305931826191777 ] } },
{ "type": "Feature", "properties": { "id": 7, "cluster_id": "39", "column": null, "row": "A" }, "geometry": { "type": "Point", "coordinates": [ 120.975848892659414, 14.305932252536731 ] } },
{ "type": "Feature", "properties": { "id": 8, "cluster_id": "39", "column": null, "row": "A" }, "geometry": { "type": "Point", "coordinates": [ 120.975856225808371, 14.305932963111642 ] } },
{ "type": "Feature", "properties": { "id": 9, "cluster_id": "39", "column": null, "row": "A" }, "geometry": { "type": "Point", "coordinates": [ 120.975866932205861, 14.30593353157157 ] } },
{ "type": "Feature", "properties": { "id": 10, "cluster_id": "39", "column": null, "row": "A" }, "geometry": { "type": "Point", "coordinates": [ 120.975875291995692, 14.305933957916514 ] } },
{ "type": "Feature", "properties": { "id": 11, "cluster_id": "39", "column": null, "row": "A" }, "geometry": { "type": "Point", "coordinates": [ 120.975882918470617, 14.305934526376442 ] } },
{ "type": "Feature", "properties": { "id": 12, "cluster_id": "39", "column": null, "row": "A" }, "geometry": { "type": "Point", "coordinates": [ 120.975889371641713, 14.305935094836368 ] } },
{ "type": "Feature", "properties": { "id": 13, "cluster_id": "39", "column": null, "row": "A" }, "geometry": { "type": "Point", "coordinates": [ 120.975897438105576, 14.305935663296291 ] } },
{ "type": "Feature", "properties": { "id": 14, "cluster_id": "39", "column": null, "row": "A" }, "geometry": { "type": "Point", "coordinates": [ 120.975906237884317, 14.305936089641229 ] } },
{ "type": "Feature", "properties": { "id": 15, "cluster_id": "39", "column": null, "row": "A" }, "geometry": { "type": "Point", "coordinates": [ 120.975914011022255, 14.305936373871196 ] } },
{ "type": "Feature", "properties": { "id": 16, "cluster_id": "39", "column": null, "row": "A" }, "geometry": { "type": "Point", "coordinates": [ 120.975921417502704, 14.305936942331114 ] } },
{ "type": "Feature", "properties": { "id": 17, "cluster_id": "39", "column": null, "row": "A" }, "geometry": { "type": "Point", "coordinates": [ 120.975933957187422, 14.305937795020991 ] } },
{ "type": "Feature", "properties": { "id": 18, "cluster_id": "39", "column": null, "row": "A" }, "geometry": { "type": "Point", "coordinates": [ 120.975946570203647, 14.305938647710866 ] } },
{ "type": "Feature", "properties": { "id": 19, "cluster_id": "39", "column": null, "row": "A" }, "geometry": { "type": "Point", "coordinates": [ 120.9759640230982, 14.30593964251571 ] } },
{ "type": "Feature", "properties": { "id": 20, "cluster_id": "39", "column": null, "row": "A" }, "geometry": { "type": "Point", "coordinates": [ 120.975982355970601, 14.305940921550508 ] } },
{ "type": "Feature", "properties": { "id": 21, "cluster_id": "39", "column": null, "row": "A" }, "geometry": { "type": "Point", "coordinates": [ 120.975993867740215, 14.305941743677181 ] } },
{ "type": "Feature", "properties": { "id": 22, "cluster_id": "39", "column": null, "row": "A" }, "geometry": { "type": "Point", "coordinates": [ 120.975994968986839, 14.305924436212544 ] } },
{ "type": "Feature", "properties": { "id": 23, "cluster_id": "39", "column": null, "row": "A" }, "geometry": { "type": "Point", "coordinates": [ 120.975995848964686, 14.305917756808027 ] } }
]
}
